astric/__init__.py
astric/astric.py
astric/loop.py
astric/parse.py
astric-1.0.0.dist-info/LICENSE
astric-1.0.0.dist-info/METADATA
astric-1.0.0.dist-info/WHEEL
astric-1.0.0.dist-info/entry_points.txt
astric-1.0.0.dist-info/top_level.txt
astric-1.0.0.dist-info/RECORD
