Metadata-Version: 2.1
Name: astric
Version: 1.0.0
Summary: Next generation CSS
Home-page: https://github.com/zanderlewis/astric
Author: Zander Lewis
Author-email: zander@zanderlewis.dev
Classifier: Programming Language :: Python :: 3
Classifier: License :: OSI Approved :: Apache Software License
Classifier: Operating System :: OS Independent
Requires-Python: >=3.6
License-File: LICENSE
